PyDigiPio.py
PyDigiPio-20.146.171707.dist-info/LICENSE
PyDigiPio-20.146.171707.dist-info/METADATA
PyDigiPio-20.146.171707.dist-info/WHEEL
PyDigiPio-20.146.171707.dist-info/top_level.txt
PyDigiPio-20.146.171707.dist-info/RECORD
