Metadata-Version: 2.1
Name: PyDigiPio
Version: 20.146.171707
Summary: Python module for Raspberry Pi GPIO
Home-page: https://github.com/EinarArnason/PyDigiPio
Author: Einar Arnason
Author-email: einsiarna@gmail.com
License: MIT License
Platform: linux
